gui/__init__.py
gui/__main__.py
gui/login.py
gui/main.py
imagebot/__init__.py
imagebot/__main__.py
imagebot/config.py
imagebot/run.py
imagebot/settings.py
imagebot/utils.py
imagebot/watermark.py
maisbot-1.3.9.dist-info/DESCRIPTION.rst
maisbot-1.3.9.dist-info/METADATA
maisbot-1.3.9.dist-info/RECORD
maisbot-1.3.9.dist-info/WHEEL
maisbot-1.3.9.dist-info/entry_points.txt
maisbot-1.3.9.dist-info/metadata.json
maisbot-1.3.9.dist-info/top_level.txt
