Metadata-Version: 2.0
Name: maisbot
Version: 1.3.9
Summary: MaisBot
Home-page: UNKNOWN
Author: Chris Maillefaud
Author-email: UNKNOWN
License: UNKNOWN
Keywords: pillow image editing watermark
Platform: UNKNOWN
Classifier: Development Status :: 4 - Beta
Classifier: Intended Audience :: Developers
Classifier: Topic :: Software Development :: Build Tools
Classifier: Programming Language :: Python :: 3.5
Requires-Dist: Pillow
Requires-Dist: colorama
Requires-Dist: docopt
